{
  "assetsByChunkName": {
    "vendors~app-account~app-checkout~app-confirmation~app-order": "chunk.de7edc2456a721384d42.js",
    "vendors~app-account~app-confirmation~app-order": "chunk.37f42568872d02755b7a.js",
    "vendors~app-account~app-checkout": "chunk.a1db34f8bb0574ef3cfb.js",
    "vendors~app-cart~app-checkout": "chunk.5852b9b3adf37f6010ed.js",
    "admin": [
      "admin.fd1c532ad8b2c363574b.js",
      "admin.fd1c532ad8b2c363574b.js.map"
    ],
    "app-account": "chunk.5ed9202f3716b23a8330.js",
    "app-cart": "chunk.9c7de5c4bd9f1b29bac9.js",
    "app-checkout": "chunk.ed7d82c6fda0db4867cc.js",
    "app-confirmation": "chunk.fea48f26577a098dc890.js",
    "app-order": "chunk.bc1dddf0d2c27acd3af2.js",
    "checkout": [
      "checkout.47f1001a73c595ef2e5b.js",
      "checkout.47f1001a73c595ef2e5b.js.map"
    ],
    "storefront": [
      "storefront.d52ea4e27901a24302a6.css",
      "storefront.96deaba1ad60243b28ae.js",
      "storefront.d52ea4e27901a24302a6.css.map",
      "storefront.96deaba1ad60243b28ae.js.map"
    ],
    "vendors~app-cart": "chunk.c80ad254aa9d18b82d68.js"
  }
}