{
  "topbar_timer": {
    "cta_url": "https://loja.foison.com.br/equipamentos",
    "start": "",
    "color": "#ffffff",
    "background_image": "",
    "background_color": "#5d539f",
    "cta_color": "#ffffff",
    "title": "Toda a linha de Plotter de Recorte com FRETE GRÁTIS PARA TODO O BRASIL!",
    "end": "",
    "cta_text": "APROVEITAR AGORA",
    "cta_background": "#5d539f"
  },
  "topbar_1": {
    "background": "#332c69",
    "color": "#ffffff",
    "topbar_1": [
      {
        "title": "A única com <b>2 anos de garantia</b>",
        "url": "/"
      },
      {
        "title": "Parcele sua Foison em <b>até 18x sem juros</b>"
      },
      {
        "title": "A Plotter de Recorte Profissional perfeita para você",
        "url": "https://loja.foison.com.br/equipamentos"
      }
    ]
  },
  "topbar_2": {
    "color": "#ffffff",
    "background": "#5c52ab"
  }
}